{
  "competitionSlug": "premier-league",
  "exportedAt": "2026-03-13T22:53:11.223Z",
  "seasonSlug": "2015/16",
  "targets": [
    {
      "competitionSeasonId": "232",
      "contractId": "12138",
      "playerName": "Aaron Cresswell",
      "playerNames": [
        "Aaron Cresswell"
      ],
      "playerSlug": "aaron-cresswell",
      "teamName": "West Ham United FC",
      "teamNames": [
        "West Ham United FC",
        "West Ham",
        "west-ham-united-fc-england"
      ],
      "teamSlug": "west-ham-united-fc-england"
    },
    {
      "competitionSeasonId": "232",
      "contractId": "11865",
      "playerName": "Aaron Lennon",
      "playerNames": [
        "Aaron Lennon"
      ],
      "playerSlug": "aaron-lennon",
      "teamName": "Everton FC",
      "teamNames": [
        "Everton FC",
        "Everton",
        "everton-fc-england"
      ],
      "teamSlug": "everton-fc-england"
    },
    {
      "competitionSeasonId": "232",
      "contractId": "11919",
      "playerName": "Aaron Ramsey",
      "playerNames": [
        "Aaron Ramsey"
      ],
      "playerSlug": "aaron-ramsey",
      "teamName": "Arsenal FC",
      "teamNames": [
        "Arsenal FC",
        "Arsenal",
        "arsenal-fc-england"
      ],
      "teamSlug": "arsenal-fc-england"
    },
    {
      "competitionSeasonId": "232",
      "contractId": "11827",
      "playerName": "Adama Traoré",
      "playerNames": [
        "Adama Traoré",
        "Adama Traoré Diarra"
      ],
      "playerSlug": "adama-traore-diarra",
      "teamName": "Aston Villa",
      "teamNames": [
        "Aston Villa",
        "aston-villa"
      ],
      "teamSlug": "aston-villa"
    },
    {
      "competitionSeasonId": "232",
      "contractId": "11944",
      "playerName": "Ádám Bogdán",
      "playerNames": [
        "Ádám Bogdán"
      ],
      "playerSlug": "adam-bogdan",
      "teamName": "Liverpool",
      "teamNames": [
        "Liverpool",
        "liverpool"
      ],
      "teamSlug": "liverpool"
    }
  ]
}
